{
  "category_key": "baby_wipes",
  "category_name": "아기물티슈",
  "guide": {
    "title": "아기물티슈 선택 가이드",
    "summary": "두께감과 성분 안전성이 가장 중요한 선택 기준입니다.",
    "key_points": [
      "도톰한 엠보싱으로 한 장만 사용",
      "캡형으로 마지막까지 촉촉하게",
      "저자극 성분으로 민감한 피부 보호",
      "적절한 수분감으로 끈적임 없이"
    ],
    "trend": "베베숲, 브라운 프리미엄, 도리도리 패턴플레이가 인기이며, 친환경 생분해 원단 제품이 주목받고 있습니다."
  },
  "pros": [
    {
      "id": "pro_1",
      "rank": 1,
      "mention_rate": 52,
      "text": "도톰하고 두꺼운 엠보싱 원단으로 한 장만으로도 충분히 깨끗하게 닦여서 매수를 덜 사용하게 돼요",
      "keywords": [
        "도톰함",
        "두께",
        "엠보싱",
        "경제적"
      ],
      "related_products": [
        "베베숲",
        "브라운 프리미엄 옐로우",
        "도리도리 패턴플레이"
      ]
    },
    {
      "id": "pro_2",
      "rank": 2,
      "mention_rate": 48,
      "text": "캡형 디자인으로 마지막 한 장까지 촉촉함이 유지되어서 건조함 걱정 없이 쓸 수 있어요",
      "keywords": [
        "캡형",
        "촉촉함유지",
        "건조방지"
      ],
      "related_products": []
    },
    {
      "id": "pro_3",
      "rank": 3,
      "mention_rate": 46,
      "text": "성분이 안전하고 저자극이라 신생아부터 민감한 피부 아이들도 안심하고 사용할 수 있어요",
      "keywords": [
        "저자극",
        "안전성분",
        "신생아사용",
        "EWG"
      ],
      "related_products": [
        "베베숲",
        "브라운 네이처 센시티브"
      ]
    },
    {
      "id": "pro_4",
      "rank": 4,
      "mention_rate": 44,
      "text": "적절한 수분감으로 과습하지도 건조하지도 않아서 사용 후 끈적임이 남지 않아요",
      "keywords": [
        "적절한수분",
        "끈적임없음",
        "밸런스"
      ],
      "related_products": []
    },
    {
      "id": "pro_5",
      "rank": 5,
      "mention_rate": 42,
      "text": "부드러운 촉감이라 아기 피부를 닦아줄 때 거부감이 적고 자극 없이 사용할 수 있어요",
      "keywords": [
        "부드러움",
        "촉감",
        "자극없음"
      ],
      "related_products": []
    },
    {
      "id": "pro_6",
      "rank": 6,
      "mention_rate": 38,
      "text": "흡수력이 뛰어나서 한 번 닦으면 여러 번 문질러도 효과적으로 오염물을 제거해요",
      "keywords": [
        "흡수력",
        "닦임성",
        "세정력"
      ],
      "related_products": []
    },
    {
      "id": "pro_7",
      "rank": 7,
      "mention_rate": 36,
      "text": "가격이 합리적이고 대용량으로 오래 쓸 수 있어서 가성비가 뛰어나요",
      "keywords": [
        "가성비",
        "대용량",
        "합리적가격"
      ],
      "related_products": [
        "도리도리 퓨어",
        "워터 99"
      ]
    },
    {
      "id": "pro_8",
      "rank": 8,
      "mention_rate": 34,
      "text": "연속으로 끊김 없이 부드럽게 한 장씩 쏙쏙 뽑혀서 사용이 편리해요",
      "keywords": [
        "한장씩뽑힘",
        "편리함",
        "끊김없음"
      ],
      "related_products": []
    },
    {
      "id": "pro_9",
      "rank": 9,
      "mention_rate": 32,
      "text": "휴대하기 편한 사이즈와 가벼운 무게로 외출할 때 가지고 다니기 좋아요",
      "keywords": [
        "휴대성",
        "가벼움",
        "외출용"
      ],
      "related_products": []
    },
    {
      "id": "pro_10",
      "rank": 10,
      "mention_rate": 30,
      "text": "에코 포장이나 생분해 원단 사용으로 환경을 생각하는 브랜드 철학이 좋아요",
      "keywords": [
        "친환경",
        "생분해",
        "에코포장"
      ],
      "related_products": [
        "프랑프랑",
        "베베숲 에코"
      ]
    }
  ],
  "cons": [
    {
      "id": "con_1",
      "rank": 1,
      "mention_rate": 38,
      "text": "프리미엄 라인의 가격이 일반 물티슈에 비해 2~3배 비싼 편이에요",
      "keywords": [
        "고가",
        "프리미엄가격",
        "비쌈"
      ],
      "deal_breaker_for": "예산이 제한된 가정"
    },
    {
      "id": "con_2",
      "rank": 2,
      "mention_rate": 36,
      "text": "가끔 물티슈가 여러 장씩 끌려나오는 경우가 있어서 짜증나요",
      "keywords": [
        "여러장뽑힘",
        "불편함",
        "낭비"
      ],
      "deal_breaker_for": "경제적 사용이 중요한 경우"
    },
    {
      "id": "con_3",
      "rank": 3,
      "mention_rate": 34,
      "text": "수분이 부족한 제품은 닦임성이 떨어져서 한 장으로 부족할 때가 있어요",
      "keywords": [
        "수분부족",
        "닦임성저하",
        "건조"
      ],
      "deal_breaker_for": "효과적인 세정이 필요한 경우"
    },
    {
      "id": "con_4",
      "rank": 4,
      "mention_rate": 32,
      "text": "너무 얇은 원단은 아기 피부를 닦을 때 손에 묻을 위험이 있어요",
      "keywords": [
        "얇음",
        "손묻음",
        "두께부족"
      ],
      "deal_breaker_for": "위생을 최우선으로 생각하는 부모"
    },
    {
      "id": "con_5",
      "rank": 5,
      "mention_rate": 30,
      "text": "보풀이 나오거나 티슈 조각이 떨어지는 경우가 있어요",
      "keywords": [
        "보풀",
        "조각떨어짐",
        "품질"
      ],
      "deal_breaker_for": "피부가 민감한 아기"
    },
    {
      "id": "con_6",
      "rank": 6,
      "mention_rate": 28,
      "text": "수분이 과다한 제품은 끈적이고 뒷처리가 불편해요",
      "keywords": [
        "과습",
        "끈적임",
        "불편함"
      ],
      "deal_breaker_for": "빠른 사용이 필요한 경우"
    },
    {
      "id": "con_7",
      "rank": 7,
      "mention_rate": 26,
      "text": "캡형의 스티커를 떼는 게 첫 사용 때 어려울 수 있어요",
      "keywords": [
        "스티커제거",
        "첫사용어려움",
        "캡"
      ],
      "deal_breaker_for": "간편한 사용을 원하는 경우"
    },
    {
      "id": "con_8",
      "rank": 8,
      "mention_rate": 22,
      "text": "아기 피부에 민감한 반응이 나타나는 경우가 있어요",
      "keywords": [
        "피부반응",
        "알레르기",
        "민감반응"
      ],
      "deal_breaker_for": "아토피나 민감 피부 아기"
    }
  ],
  "tradeoffs": [],
  "question_context": {
    "typical_use_cases": [
      "기저귀 갈 때 엉덩이 닦기",
      "외출 시 손과 얼굴 닦기",
      "이유식 후 입 주변 청소"
    ],
    "common_concerns": [
      "피부 자극과 알레르기",
      "수분 부족으로 건조함",
      "비싼 프리미엄 가격",
      "여러 장이 한 번에 뽑히는 문제"
    ],
    "decision_factors": [
      "두께와 엠보싱",
      "성분 안전성",
      "캡형 vs 스티커형",
      "가격대",
      "친환경 여부"
    ]
  }
}
